{"nodes": [{"id": "mnt_d_crushcode_src_commands_logs_zig", "label": "logs.zig", "file_type": "code", "source_file": "/mnt/d/crushcode/src/commands/logs.zig", "source_location": "L1"}, {"id": "commands_logs_handlelogs", "label": "handleLogs()", "file_type": "code", "source_file": "/mnt/d/crushcode/src/commands/logs.zig", "source_location": "L10"}, {"id": "commands_logs_parselevel", "label": "parseLevel()", "file_type": "code", "source_file": "/mnt/d/crushcode/src/commands/logs.zig", "source_location": "L70"}, {"id": "commands_logs_findlatestlogfile", "label": "findLatestLogFile()", "file_type": "code", "source_file": "/mnt/d/crushcode/src/commands/logs.zig", "source_location": "L78"}, {"id": "commands_logs_tailfile", "label": "tailFile()", "file_type": "code", "source_file": "/mnt/d/crushcode/src/commands/logs.zig", "source_location": "L110"}, {"id": "commands_logs_followfile", "label": "followFile()", "file_type": "code", "source_file": "/mnt/d/crushcode/src/commands/logs.zig", "source_location": "L141"}, {"id": "commands_logs_readfilecontents", "label": "readFileContents()", "file_type": "code", "source_file": "/mnt/d/crushcode/src/commands/logs.zig", "source_location": "L187"}, {"id": "commands_logs_linematcheslevel", "label": "lineMatchesLevel()", "file_type": "code", "source_file": "/mnt/d/crushcode/src/commands/logs.zig", "source_location": "L199"}, {"id": "commands_logs_printcoloredline", "label": "printColoredLine()", "file_type": "code", "source_file": "/mnt/d/crushcode/src/commands/logs.zig", "source_location": "L206"}, {"id": "commands_logs_getstyleforline", "label": "getStyleForLine()", "file_type": "code", "source_file": "/mnt/d/crushcode/src/commands/logs.zig", "source_location": "L233"}, {"id": "commands_logs_extractfield", "label": "extractField()", "file_type": "code", "source_file": "/mnt/d/crushcode/src/commands/logs.zig", "source_location": "L243"}], "edges": [{"source": "mnt_d_crushcode_src_commands_logs_zig", "target": "std", "relation": "imports_from", "confidence": "EXTRACTED", "source_file": "/mnt/d/crushcode/src/commands/logs.zig", "source_location": "L1", "weight": 1.0}, {"source": "mnt_d_crushcode_src_commands_logs_zig", "target": "file_compat", "relation": "imports_from", "confidence": "EXTRACTED", "source_file": "/mnt/d/crushcode/src/commands/logs.zig", "source_location": "L2", "weight": 1.0}, {"source": "mnt_d_crushcode_src_commands_logs_zig", "target": "array_list_compat", "relation": "imports_from", "confidence": "EXTRACTED", "source_file": "/mnt/d/crushcode/src/commands/logs.zig", "source_location": "L3", "weight": 1.0}, {"source": "mnt_d_crushcode_src_commands_logs_zig", "target": "env", "relation": "imports_from", "confidence": "EXTRACTED", "source_file": "/mnt/d/crushcode/src/commands/logs.zig", "source_location": "L4", "weight": 1.0}, {"source": "mnt_d_crushcode_src_commands_logs_zig", "target": "args", "relation": "imports_from", "confidence": "EXTRACTED", "source_file": "/mnt/d/crushcode/src/commands/logs.zig", "source_location": "L5", "weight": 1.0}, {"source": "mnt_d_crushcode_src_commands_logs_zig", "target": "color", "relation": "imports_from", "confidence": "EXTRACTED", "source_file": "/mnt/d/crushcode/src/commands/logs.zig", "source_location": "L6", "weight": 1.0}, {"source": "mnt_d_crushcode_src_commands_logs_zig", "target": "structured_log", "relation": "imports_from", "confidence": "EXTRACTED", "source_file": "/mnt/d/crushcode/src/commands/logs.zig", "source_location": "L8", "weight": 1.0}, {"source": "mnt_d_crushcode_src_commands_logs_zig", "target": "commands_logs_handlelogs", "relation": "contains", "confidence": "EXTRACTED", "source_file": "/mnt/d/crushcode/src/commands/logs.zig", "source_location": "L10", "weight": 1.0}, {"source": "mnt_d_crushcode_src_commands_logs_zig", "target": "commands_logs_parselevel", "relation": "contains", "confidence": "EXTRACTED", "source_file": "/mnt/d/crushcode/src/commands/logs.zig", "source_location": "L70", "weight": 1.0}, {"source": "mnt_d_crushcode_src_commands_logs_zig", "target": "commands_logs_findlatestlogfile", "relation": "contains", "confidence": "EXTRACTED", "source_file": "/mnt/d/crushcode/src/commands/logs.zig", "source_location": "L78", "weight": 1.0}, {"source": "mnt_d_crushcode_src_commands_logs_zig", "target": "commands_logs_tailfile", "relation": "contains", "confidence": "EXTRACTED", "source_file": "/mnt/d/crushcode/src/commands/logs.zig", "source_location": "L110", "weight": 1.0}, {"source": "mnt_d_crushcode_src_commands_logs_zig", "target": "commands_logs_followfile", "relation": "contains", "confidence": "EXTRACTED", "source_file": "/mnt/d/crushcode/src/commands/logs.zig", "source_location": "L141", "weight": 1.0}, {"source": "mnt_d_crushcode_src_commands_logs_zig", "target": "commands_logs_readfilecontents", "relation": "contains", "confidence": "EXTRACTED", "source_file": "/mnt/d/crushcode/src/commands/logs.zig", "source_location": "L187", "weight": 1.0}, {"source": "mnt_d_crushcode_src_commands_logs_zig", "target": "commands_logs_linematcheslevel", "relation": "contains", "confidence": "EXTRACTED", "source_file": "/mnt/d/crushcode/src/commands/logs.zig", "source_location": "L199", "weight": 1.0}, {"source": "mnt_d_crushcode_src_commands_logs_zig", "target": "commands_logs_printcoloredline", "relation": "contains", "confidence": "EXTRACTED", "source_file": "/mnt/d/crushcode/src/commands/logs.zig", "source_location": "L206", "weight": 1.0}, {"source": "mnt_d_crushcode_src_commands_logs_zig", "target": "commands_logs_getstyleforline", "relation": "contains", "confidence": "EXTRACTED", "source_file": "/mnt/d/crushcode/src/commands/logs.zig", "source_location": "L233", "weight": 1.0}, {"source": "mnt_d_crushcode_src_commands_logs_zig", "target": "commands_logs_extractfield", "relation": "contains", "confidence": "EXTRACTED", "source_file": "/mnt/d/crushcode/src/commands/logs.zig", "source_location": "L243", "weight": 1.0}, {"source": "commands_logs_handlelogs", "target": "commands_logs_parselevel", "relation": "calls", "confidence": "EXTRACTED", "source_file": "/mnt/d/crushcode/src/commands/logs.zig", "source_location": "L33", "weight": 1.0}, {"source": "commands_logs_handlelogs", "target": "commands_logs_findlatestlogfile", "relation": "calls", "confidence": "EXTRACTED", "source_file": "/mnt/d/crushcode/src/commands/logs.zig", "source_location": "L49", "weight": 1.0}, {"source": "commands_logs_handlelogs", "target": "commands_logs_followfile", "relation": "calls", "confidence": "EXTRACTED", "source_file": "/mnt/d/crushcode/src/commands/logs.zig", "source_location": "L64", "weight": 1.0}, {"source": "commands_logs_handlelogs", "target": "commands_logs_tailfile", "relation": "calls", "confidence": "EXTRACTED", "source_file": "/mnt/d/crushcode/src/commands/logs.zig", "source_location": "L66", "weight": 1.0}, {"source": "commands_logs_tailfile", "target": "commands_logs_readfilecontents", "relation": "calls", "confidence": "EXTRACTED", "source_file": "/mnt/d/crushcode/src/commands/logs.zig", "source_location": "L111", "weight": 1.0}, {"source": "commands_logs_tailfile", "target": "commands_logs_printcoloredline", "relation": "calls", "confidence": "EXTRACTED", "source_file": "/mnt/d/crushcode/src/commands/logs.zig", "source_location": "L137", "weight": 1.0}, {"source": "commands_logs_followfile", "target": "commands_logs_readfilecontents", "relation": "calls", "confidence": "EXTRACTED", "source_file": "/mnt/d/crushcode/src/commands/logs.zig", "source_location": "L145", "weight": 1.0}, {"source": "commands_logs_followfile", "target": "commands_logs_printcoloredline", "relation": "calls", "confidence": "EXTRACTED", "source_file": "/mnt/d/crushcode/src/commands/logs.zig", "source_location": "L159", "weight": 1.0}, {"source": "commands_logs_printcoloredline", "target": "commands_logs_getstyleforline", "relation": "calls", "confidence": "EXTRACTED", "source_file": "/mnt/d/crushcode/src/commands/logs.zig", "source_location": "L208", "weight": 1.0}, {"source": "commands_logs_printcoloredline", "target": "commands_logs_extractfield", "relation": "calls", "confidence": "EXTRACTED", "source_file": "/mnt/d/crushcode/src/commands/logs.zig", "source_location": "L211", "weight": 1.0}], "raw_calls": [{"caller_nid": "commands_logs_handlelogs", "callee": "eql", "source_file": "/mnt/d/crushcode/src/commands/logs.zig", "source_location": "L21"}, {"caller_nid": "commands_logs_handlelogs", "callee": "parseInt", "source_file": "/mnt/d/crushcode/src/commands/logs.zig", "source_location": "L24"}, {"caller_nid": "commands_logs_handlelogs", "callee": "startsWith", "source_file": "/mnt/d/crushcode/src/commands/logs.zig", "source_location": "L26"}, {"caller_nid": "commands_logs_handlelogs", "callee": "parseInt", "source_file": "/mnt/d/crushcode/src/commands/logs.zig", "source_location": "L27"}, {"caller_nid": "commands_logs_handlelogs", "callee": "eql", "source_file": "/mnt/d/crushcode/src/commands/logs.zig", "source_location": "L28"}, {"caller_nid": "commands_logs_handlelogs", "callee": "eql", "source_file": "/mnt/d/crushcode/src/commands/logs.zig", "source_location": "L28"}, {"caller_nid": "commands_logs_handlelogs", "callee": "eql", "source_file": "/mnt/d/crushcode/src/commands/logs.zig", "source_location": "L30"}, {"caller_nid": "commands_logs_handlelogs", "callee": "startsWith", "source_file": "/mnt/d/crushcode/src/commands/logs.zig", "source_location": "L35"}, {"caller_nid": "commands_logs_handlelogs", "callee": "getLogDir", "source_file": "/mnt/d/crushcode/src/commands/logs.zig", "source_location": "L41"}, {"caller_nid": "commands_logs_handlelogs", "callee": "stderr", "source_file": "/mnt/d/crushcode/src/commands/logs.zig", "source_location": "L42"}, {"caller_nid": "commands_logs_handlelogs", "callee": "print", "source_file": "/mnt/d/crushcode/src/commands/logs.zig", "source_location": "L43"}, {"caller_nid": "commands_logs_handlelogs", "callee": "free", "source_file": "/mnt/d/crushcode/src/commands/logs.zig", "source_location": "L46"}, {"caller_nid": "commands_logs_handlelogs", "callee": "stderr", "source_file": "/mnt/d/crushcode/src/commands/logs.zig", "source_location": "L50"}, {"caller_nid": "commands_logs_handlelogs", "callee": "print", "source_file": "/mnt/d/crushcode/src/commands/logs.zig", "source_location": "L52"}, {"caller_nid": "commands_logs_handlelogs", "callee": "print", "source_file": "/mnt/d/crushcode/src/commands/logs.zig", "source_location": "L54"}, {"caller_nid": "commands_logs_handlelogs", "callee": "free", "source_file": "/mnt/d/crushcode/src/commands/logs.zig", "source_location": "L58"}, {"caller_nid": "commands_logs_handlelogs", "callee": "join", "source_file": "/mnt/d/crushcode/src/commands/logs.zig", "source_location": "L60"}, {"caller_nid": "commands_logs_handlelogs", "callee": "free", "source_file": "/mnt/d/crushcode/src/commands/logs.zig", "source_location": "L61"}, {"caller_nid": "commands_logs_parselevel", "callee": "eql", "source_file": "/mnt/d/crushcode/src/commands/logs.zig", "source_location": "L71"}, {"caller_nid": "commands_logs_parselevel", "callee": "eql", "source_file": "/mnt/d/crushcode/src/commands/logs.zig", "source_location": "L71"}, {"caller_nid": "commands_logs_parselevel", "callee": "eql", "source_file": "/mnt/d/crushcode/src/commands/logs.zig", "source_location": "L72"}, {"caller_nid": "commands_logs_parselevel", "callee": "eql", "source_file": "/mnt/d/crushcode/src/commands/logs.zig", "source_location": "L72"}, {"caller_nid": "commands_logs_parselevel", "callee": "eql", "source_file": "/mnt/d/crushcode/src/commands/logs.zig", "source_location": "L73"}, {"caller_nid": "commands_logs_parselevel", "callee": "eql", "source_file": "/mnt/d/crushcode/src/commands/logs.zig", "source_location": "L73"}, {"caller_nid": "commands_logs_parselevel", "callee": "eql", "source_file": "/mnt/d/crushcode/src/commands/logs.zig", "source_location": "L74"}, {"caller_nid": "commands_logs_parselevel", "callee": "eql", "source_file": "/mnt/d/crushcode/src/commands/logs.zig", "source_location": "L74"}, {"caller_nid": "commands_logs_parselevel", "callee": "eql", "source_file": "/mnt/d/crushcode/src/commands/logs.zig", "source_location": "L74"}, {"caller_nid": "commands_logs_parselevel", "callee": "eql", "source_file": "/mnt/d/crushcode/src/commands/logs.zig", "source_location": "L74"}, {"caller_nid": "commands_logs_findlatestlogfile", "callee": "openDir", "source_file": "/mnt/d/crushcode/src/commands/logs.zig", "source_location": "L79"}, {"caller_nid": "commands_logs_findlatestlogfile", "callee": "cwd", "source_file": "/mnt/d/crushcode/src/commands/logs.zig", "source_location": "L79"}, {"caller_nid": "commands_logs_findlatestlogfile", "callee": "close", "source_file": "/mnt/d/crushcode/src/commands/logs.zig", "source_location": "L80"}, {"caller_nid": "commands_logs_findlatestlogfile", "callee": "init", "source_file": "/mnt/d/crushcode/src/commands/logs.zig", "source_location": "L82"}, {"caller_nid": "commands_logs_findlatestlogfile", "callee": "ArrayList", "source_file": "/mnt/d/crushcode/src/commands/logs.zig", "source_location": "L82"}, {"caller_nid": "commands_logs_findlatestlogfile", "callee": "free", "source_file": "/mnt/d/crushcode/src/commands/logs.zig", "source_location": "L84"}, {"caller_nid": "commands_logs_findlatestlogfile", "callee": "deinit", "source_file": "/mnt/d/crushcode/src/commands/logs.zig", "source_location": "L85"}, {"caller_nid": "commands_logs_findlatestlogfile", "callee": "iterate", "source_file": "/mnt/d/crushcode/src/commands/logs.zig", "source_location": "L88"}, {"caller_nid": "commands_logs_findlatestlogfile", "callee": "next", "source_file": "/mnt/d/crushcode/src/commands/logs.zig", "source_location": "L89"}, {"caller_nid": "commands_logs_findlatestlogfile", "callee": "startsWith", "source_file": "/mnt/d/crushcode/src/commands/logs.zig", "source_location": "L91"}, {"caller_nid": "commands_logs_findlatestlogfile", "callee": "endsWith", "source_file": "/mnt/d/crushcode/src/commands/logs.zig", "source_location": "L92"}, {"caller_nid": "commands_logs_findlatestlogfile", "callee": "dupe", "source_file": "/mnt/d/crushcode/src/commands/logs.zig", "source_location": "L93"}, {"caller_nid": "commands_logs_findlatestlogfile", "callee": "append", "source_file": "/mnt/d/crushcode/src/commands/logs.zig", "source_location": "L94"}, {"caller_nid": "commands_logs_findlatestlogfile", "callee": "block", "source_file": "/mnt/d/crushcode/src/commands/logs.zig", "source_location": "L101"}, {"caller_nid": "commands_logs_findlatestlogfile", "callee": "dupe", "source_file": "/mnt/d/crushcode/src/commands/logs.zig", "source_location": "L107"}, {"caller_nid": "commands_logs_tailfile", "callee": "stderr", "source_file": "/mnt/d/crushcode/src/commands/logs.zig", "source_location": "L112"}, {"caller_nid": "commands_logs_tailfile", "callee": "print", "source_file": "/mnt/d/crushcode/src/commands/logs.zig", "source_location": "L113"}, {"caller_nid": "commands_logs_tailfile", "callee": "free", "source_file": "/mnt/d/crushcode/src/commands/logs.zig", "source_location": "L116"}, {"caller_nid": "commands_logs_tailfile", "callee": "init", "source_file": "/mnt/d/crushcode/src/commands/logs.zig", "source_location": "L118"}, {"caller_nid": "commands_logs_tailfile", "callee": "ArrayList", "source_file": "/mnt/d/crushcode/src/commands/logs.zig", "source_location": "L118"}, {"caller_nid": "commands_logs_tailfile", "callee": "deinit", "source_file": "/mnt/d/crushcode/src/commands/logs.zig", "source_location": "L119"}, {"caller_nid": "commands_logs_tailfile", "callee": "splitSequence", "source_file": "/mnt/d/crushcode/src/commands/logs.zig", "source_location": "L122"}, {"caller_nid": "commands_logs_tailfile", "callee": "next", "source_file": "/mnt/d/crushcode/src/commands/logs.zig", "source_location": "L123"}, {"caller_nid": "commands_logs_tailfile", "callee": "!lineMatchesLevel", "source_file": "/mnt/d/crushcode/src/commands/logs.zig", "source_location": "L127"}, {"caller_nid": "commands_logs_tailfile", "callee": "append", "source_file": "/mnt/d/crushcode/src/commands/logs.zig", "source_location": "L129"}, {"caller_nid": "commands_logs_tailfile", "callee": "stdout", "source_file": "/mnt/d/crushcode/src/commands/logs.zig", "source_location": "L132"}, {"caller_nid": "commands_logs_followfile", "callee": "stdout", "source_file": "/mnt/d/crushcode/src/commands/logs.zig", "source_location": "L142"}, {"caller_nid": "commands_logs_followfile", "callee": "stderr", "source_file": "/mnt/d/crushcode/src/commands/logs.zig", "source_location": "L146"}, {"caller_nid": "commands_logs_followfile", "callee": "print", "source_file": "/mnt/d/crushcode/src/commands/logs.zig", "source_location": "L147"}, {"caller_nid": "commands_logs_followfile", "callee": "free", "source_file": "/mnt/d/crushcode/src/commands/logs.zig", "source_location": "L150"}, {"caller_nid": "commands_logs_followfile", "callee": "splitSequence", "source_file": "/mnt/d/crushcode/src/commands/logs.zig", "source_location": "L153"}, {"caller_nid": "commands_logs_followfile", "callee": "next", "source_file": "/mnt/d/crushcode/src/commands/logs.zig", "source_location": "L154"}, {"caller_nid": "commands_logs_followfile", "callee": "!lineMatchesLevel", "source_file": "/mnt/d/crushcode/src/commands/logs.zig", "source_location": "L157"}, {"caller_nid": "commands_logs_followfile", "callee": "sleep", "source_file": "/mnt/d/crushcode/src/commands/logs.zig", "source_location": "L167"}, {"caller_nid": "commands_logs_followfile", "callee": "free", "source_file": "/mnt/d/crushcode/src/commands/logs.zig", "source_location": "L170"}, {"caller_nid": "commands_logs_followfile", "callee": "splitSequence", "source_file": "/mnt/d/crushcode/src/commands/logs.zig", "source_location": "L174"}, {"caller_nid": "commands_logs_followfile", "callee": "next", "source_file": "/mnt/d/crushcode/src/commands/logs.zig", "source_location": "L175"}, {"caller_nid": "commands_logs_followfile", "callee": "!lineMatchesLevel", "source_file": "/mnt/d/crushcode/src/commands/logs.zig", "source_location": "L178"}, {"caller_nid": "commands_logs_readfilecontents", "callee": "openFile", "source_file": "/mnt/d/crushcode/src/commands/logs.zig", "source_location": "L188"}, {"caller_nid": "commands_logs_readfilecontents", "callee": "cwd", "source_file": "/mnt/d/crushcode/src/commands/logs.zig", "source_location": "L188"}, {"caller_nid": "commands_logs_readfilecontents", "callee": "close", "source_file": "/mnt/d/crushcode/src/commands/logs.zig", "source_location": "L189"}, {"caller_nid": "commands_logs_readfilecontents", "callee": "stat", "source_file": "/mnt/d/crushcode/src/commands/logs.zig", "source_location": "L191"}, {"caller_nid": "commands_logs_readfilecontents", "callee": "dupe", "source_file": "/mnt/d/crushcode/src/commands/logs.zig", "source_location": "L192"}, {"caller_nid": "commands_logs_readfilecontents", "callee": "alloc", "source_file": "/mnt/d/crushcode/src/commands/logs.zig", "source_location": "L194"}, {"caller_nid": "commands_logs_readfilecontents", "callee": "readAll", "source_file": "/mnt/d/crushcode/src/commands/logs.zig", "source_location": "L195"}, {"caller_nid": "commands_logs_readfilecontents", "callee": "realloc", "source_file": "/mnt/d/crushcode/src/commands/logs.zig", "source_location": "L196"}, {"caller_nid": "commands_logs_linematcheslevel", "callee": "allocPrint", "source_file": "/mnt/d/crushcode/src/commands/logs.zig", "source_location": "L201"}, {"caller_nid": "commands_logs_linematcheslevel", "callee": "asString", "source_file": "/mnt/d/crushcode/src/commands/logs.zig", "source_location": "L201"}, {"caller_nid": "commands_logs_linematcheslevel", "callee": "free", "source_file": "/mnt/d/crushcode/src/commands/logs.zig", "source_location": "L202"}, {"caller_nid": "commands_logs_linematcheslevel", "callee": "indexOf", "source_file": "/mnt/d/crushcode/src/commands/logs.zig", "source_location": "L203"}, {"caller_nid": "commands_logs_printcoloredline", "callee": "print", "source_file": "/mnt/d/crushcode/src/commands/logs.zig", "source_location": "L217"}, {"caller_nid": "commands_logs_printcoloredline", "callee": "start", "source_file": "/mnt/d/crushcode/src/commands/logs.zig", "source_location": "L217"}, {"caller_nid": "commands_logs_printcoloredline", "callee": "reset", "source_file": "/mnt/d/crushcode/src/commands/logs.zig", "source_location": "L217"}, {"caller_nid": "commands_logs_printcoloredline", "callee": "print", "source_file": "/mnt/d/crushcode/src/commands/logs.zig", "source_location": "L220"}, {"caller_nid": "commands_logs_printcoloredline", "callee": "start", "source_file": "/mnt/d/crushcode/src/commands/logs.zig", "source_location": "L220"}, {"caller_nid": "commands_logs_printcoloredline", "callee": "reset", "source_file": "/mnt/d/crushcode/src/commands/logs.zig", "source_location": "L220"}, {"caller_nid": "commands_logs_printcoloredline", "callee": "print", "source_file": "/mnt/d/crushcode/src/commands/logs.zig", "source_location": "L223"}, {"caller_nid": "commands_logs_printcoloredline", "callee": "start", "source_file": "/mnt/d/crushcode/src/commands/logs.zig", "source_location": "L223"}, {"caller_nid": "commands_logs_printcoloredline", "callee": "reset", "source_file": "/mnt/d/crushcode/src/commands/logs.zig", "source_location": "L223"}, {"caller_nid": "commands_logs_printcoloredline", "callee": "print", "source_file": "/mnt/d/crushcode/src/commands/logs.zig", "source_location": "L226"}, {"caller_nid": "commands_logs_printcoloredline", "callee": "print", "source_file": "/mnt/d/crushcode/src/commands/logs.zig", "source_location": "L229"}, {"caller_nid": "commands_logs_getstyleforline", "callee": "indexOf", "source_file": "/mnt/d/crushcode/src/commands/logs.zig", "source_location": "L234"}, {"caller_nid": "commands_logs_getstyleforline", "callee": "indexOf", "source_file": "/mnt/d/crushcode/src/commands/logs.zig", "source_location": "L235"}, {"caller_nid": "commands_logs_getstyleforline", "callee": "indexOf", "source_file": "/mnt/d/crushcode/src/commands/logs.zig", "source_location": "L236"}, {"caller_nid": "commands_logs_getstyleforline", "callee": "indexOf", "source_file": "/mnt/d/crushcode/src/commands/logs.zig", "source_location": "L237"}, {"caller_nid": "commands_logs_extractfield", "callee": "allocPrint", "source_file": "/mnt/d/crushcode/src/commands/logs.zig", "source_location": "L244"}, {"caller_nid": "commands_logs_extractfield", "callee": "free", "source_file": "/mnt/d/crushcode/src/commands/logs.zig", "source_location": "L245"}, {"caller_nid": "commands_logs_extractfield", "callee": "indexOf", "source_file": "/mnt/d/crushcode/src/commands/logs.zig", "source_location": "L247"}, {"caller_nid": "commands_logs_extractfield", "callee": "init", "source_file": "/mnt/d/crushcode/src/commands/logs.zig", "source_location": "L264"}, {"caller_nid": "commands_logs_extractfield", "callee": "ArrayList", "source_file": "/mnt/d/crushcode/src/commands/logs.zig", "source_location": "L264"}, {"caller_nid": "commands_logs_extractfield", "callee": "deinit", "source_file": "/mnt/d/crushcode/src/commands/logs.zig", "source_location": "L265"}, {"caller_nid": "commands_logs_extractfield", "callee": "append", "source_file": "/mnt/d/crushcode/src/commands/logs.zig", "source_location": "L273"}, {"caller_nid": "commands_logs_extractfield", "callee": "append", "source_file": "/mnt/d/crushcode/src/commands/logs.zig", "source_location": "L277"}, {"caller_nid": "commands_logs_extractfield", "callee": "append", "source_file": "/mnt/d/crushcode/src/commands/logs.zig", "source_location": "L281"}, {"caller_nid": "commands_logs_extractfield", "callee": "append", "source_file": "/mnt/d/crushcode/src/commands/logs.zig", "source_location": "L285"}, {"caller_nid": "commands_logs_extractfield", "callee": "append", "source_file": "/mnt/d/crushcode/src/commands/logs.zig", "source_location": "L289"}, {"caller_nid": "commands_logs_extractfield", "callee": "append", "source_file": "/mnt/d/crushcode/src/commands/logs.zig", "source_location": "L293"}, {"caller_nid": "commands_logs_extractfield", "callee": "append", "source_file": "/mnt/d/crushcode/src/commands/logs.zig", "source_location": "L297"}, {"caller_nid": "commands_logs_extractfield", "callee": "toOwnedSlice", "source_file": "/mnt/d/crushcode/src/commands/logs.zig", "source_location": "L301"}]}